cti/__init__.py
cti/main.py
cti/main_api.py
cti/api/__init__.py
cti/api/async_client.py
cti/api/client.py
cti/api/session.py
cti/logger/__init__.py
cti/logger/logger.py
cti/model/__init__.py
cti/model/altitude_source.py
cti/model/attitude_source.py
cti/model/depth_source.py
cti/model/device.py
cti/model/device_type.py
cti/model/final_product.py
cti/model/hierarchy.py
cti/model/layback_algorithm.py
cti/model/layback_source.py
cti/model/layback_type.py
cti/model/organization.py
cti/model/platform.py
cti/model/platform_type.py
cti/model/position_source.py
cti/model/processed_altitude.py
cti/model/processed_attitude.py
cti/model/processed_depth.py
cti/model/processed_layback.py
cti/model/processed_position.py
cti/model/processed_sidescan_ping.py
cti/model/processing_log.py
cti/model/project.py
cti/model/projection_option.py
cti/model/raw_altitude.py
cti/model/raw_attitude.py
cti/model/raw_depth.py
cti/model/raw_file.py
cti/model/raw_file_configuration.py
cti/model/raw_layback.py
cti/model/raw_position.py
cti/model/raw_sidescan_ping.py
cti/model/s3.py
cti/model/sidescan_ping_source.py
cti/model/source.py
cti/model/survey.py
cti/model/target.py
cti/model/tow_system.py
clarity_api_sdk_python-0.3.16.dist-info/METADATA
clarity_api_sdk_python-0.3.16.dist-info/WHEEL
clarity_api_sdk_python-0.3.16.dist-info/top_level.txt
clarity_api_sdk_python-0.3.16.dist-info/RECORD
