Metadata-Version: 2.4
Name: clarity-api-sdk-python
Version: 0.3.16
Summary: A Python SDK to connect to the CTI Clarity API server.
Author-email: "Chesapeake Technology Inc." <support@chesapeaketech.com>
Project-URL: Homepage, https://github.com/chesapeake-tech/clarity-api-sdk-python
Classifier: Programming Language :: Python :: 3
Classifier: License :: OSI Approved :: MIT License
Classifier: Operating System :: OS Independent
Requires-Python: >=3.11
Requires-Dist: httpx>=0.28.1
Requires-Dist: brotli
Requires-Dist: h2
Requires-Dist: httpx_auth>=0.23.1
Requires-Dist: httpx-retries>=0.4.5
Requires-Dist: pydantic==2.12.3
Requires-Dist: structlog
Provides-Extra: dev
Requires-Dist: black==25.9.0; extra == "dev"
Requires-Dist: build==1.3.0; extra == "dev"
Requires-Dist: mypy==1.18.2; extra == "dev"
Requires-Dist: pre-commit==4.3.0; extra == "dev"
Requires-Dist: pylint==3.3.8; extra == "dev"
Requires-Dist: pytest==8.4.2; extra == "dev"
Requires-Dist: pytest-asyncio==1.3.0; extra == "dev"
Requires-Dist: pytest-md==0.2.0; extra == "dev"
Requires-Dist: pytest-mock==3.15.1; extra == "dev"
Requires-Dist: twine==6.2.0; extra == "dev"
Provides-Extra: brotli
Requires-Dist: httpx[brotli]>=0.28.1; extra == "brotli"
Provides-Extra: http2
Requires-Dist: httpx[http2]>=0.28.1; extra == "http2"
